curvepy/__init__.py
curvepy/curvepy.py
curvepy/denoise.py
curvepy/filters.py
curvepy/windows.py
curvepy_fdct-1.0.0.dist-info/METADATA
curvepy_fdct-1.0.0.dist-info/WHEEL
curvepy_fdct-1.0.0.dist-info/licenses/LICENSE
curvepy_fdct-1.0.0.dist-info/RECORD
