Metadata-Version: 2.4
Name: curvepy-fdct
Version: 1.0.0
Summary: A Pure Python Clean-Room Implementation of the Fast Discrete Curvelet Transform
License: MIT License
License-File: LICENSE
Keywords: curvelet,signal-processing,denoising,wavelets
Author: Noah Munro-Kagan
Author-email: noahmunrokagan@gmail.com
Requires-Python: >=3.11
Classifier: Development Status :: 5 - Production/Stable
Classifier: Intended Audience :: Science/Research
Classifier: License :: OSI Approved :: MIT License
Classifier: Programming Language :: Python :: 3
Classifier: Topic :: Scientific/Engineering :: Image Processing
Requires-Dist: matplotlib (>=3.10.8,<4.0.0)
Requires-Dist: numpy (>=2.4.0,<3.0.0)
Requires-Dist: pywavelets (>=1.9.0,<2.0.0)
Requires-Dist: scikit-image (>=0.26.0,<0.27.0)
Project-URL: Bug Tracker, https://github.com/noahmunrokagan/curvepy/issues
Project-URL: Homepage, https://github.com/noahmunrokagan/curvepy
